pulse_recharts/__init__.py
pulse_recharts/cartesian.py
pulse_recharts/charts.py
pulse_recharts/common.py
pulse_recharts/general.py
pulse_recharts/py.typed
pulse_recharts/shapes.py
pulse_recharts-0.1.3.dist-info/WHEEL
pulse_recharts-0.1.3.dist-info/entry_points.txt
pulse_recharts-0.1.3.dist-info/METADATA
pulse_recharts-0.1.3.dist-info/RECORD
